{
  "logoType": "default",
  "logo": {
    "lucideIcon": "",
    "imagePath": "",
    "imageLink": ""
  },
  "logoScale": 1.2,
  "iconColorType": "default",
  "wordmark": "Obsidian",
  "customFont": "interfaceFont",
  "fontSize": "4em",
  "fontColorType": "default",
  "fontWeight": 600,
  "maxResults": 5,
  "showStarredFiles": true,
  "showRecentFiles": false,
  "maxRecentFiles": 5,
  "storeRecentFile": true,
  "showPath": true,
  "selectionHighlight": "default",
  "showShortcuts": true,
  "markdownOnly": false,
  "unresolvedLinks": true,
  "recentFilesStore": [
    {
      "filepath": "📐 Dự án/3 Thành phẩm/Phần mềm/Bộ cài/Hướng dẫn tải vault.md",
      "timestamp": 1683193228070
    },
    {
      "filepath": "📐 Dự án/3 Thành phẩm/Phần mềm/Bộ cài/Các trục trặc có thể gặp khi cài.md",
      "timestamp": 1683193227742
    },
    {
      "filepath": "📐 Dự án/3 Thành phẩm/Phần mềm/Bộ cài/Bộ cài.md",
      "timestamp": 1683193226597
    },
    {
      "filepath": "🌟 Mở đầu.md",
      "timestamp": 1683193040980
    },
    {
      "filepath": "📐 Dự án/3 Thành phẩm/3 Thành phẩm.md",
      "timestamp": 1683193039951
    }
  ],
  "starredFileStore": [],
  "searchDelay": 0,
  "replaceNewTabs": true,
  "newTabOnStart": false,
  "closePreviousSessionTabs": false,
  "omnisearch": false
}